{
  "ok": true,
  "frames_root": "C:\\Users\\simon\\Desktop\\MYCOOLESTSHIT\\001_testing_style\\artificial-influece\\pet-runs\\bloop\\qa\\rows\\waving\\frames",
  "states": [
    "waving"
  ],
  "errors": [],
  "warnings": [],
  "rows": [
    {
      "state": "waving",
      "expected_frames": 4,
      "actual_frames": 4,
      "extraction_method": "components",
      "ok": true,
      "errors": [],
      "warnings": [],
      "frames": [
        {
          "index": 0,
          "file": "C:\\Users\\simon\\Desktop\\MYCOOLESTSHIT\\001_testing_style\\artificial-influece\\pet-runs\\bloop\\qa\\rows\\waving\\frames\\waving\\00.png",
          "width": 192,
          "height": 208,
          "nontransparent_pixels": 20862,
          "bbox": [
            5,
            27,
            187,
            180
          ],
          "edge_pixels": 0,
          "chroma_adjacent_pixels": 61
        },
        {
          "index": 1,
          "file": "C:\\Users\\simon\\Desktop\\MYCOOLESTSHIT\\001_testing_style\\artificial-influece\\pet-runs\\bloop\\qa\\rows\\waving\\frames\\waving\\01.png",
          "width": 192,
          "height": 208,
          "nontransparent_pixels": 22128,
          "bbox": [
            5,
            21,
            187,
            186
          ],
          "edge_pixels": 0,
          "chroma_adjacent_pixels": 69
        },
        {
          "index": 2,
          "file": "C:\\Users\\simon\\Desktop\\MYCOOLESTSHIT\\001_testing_style\\artificial-influece\\pet-runs\\bloop\\qa\\rows\\waving\\frames\\waving\\02.png",
          "width": 192,
          "height": 208,
          "nontransparent_pixels": 21692,
          "bbox": [
            5,
            28,
            187,
            179
          ],
          "edge_pixels": 0,
          "chroma_adjacent_pixels": 71
        },
        {
          "index": 3,
          "file": "C:\\Users\\simon\\Desktop\\MYCOOLESTSHIT\\001_testing_style\\artificial-influece\\pet-runs\\bloop\\qa\\rows\\waving\\frames\\waving\\03.png",
          "width": 192,
          "height": 208,
          "nontransparent_pixels": 20832,
          "bbox": [
            5,
            27,
            187,
            180
          ],
          "edge_pixels": 0,
          "chroma_adjacent_pixels": 63
        }
      ]
    }
  ]
}
